{"name":"博客","postlist":[{"title":"Hexo 搭建静态博客","slug":"Install/hello-world","date":"2021-12-04T03:22:50.000Z","updated":"2023-11-29T02:42:01.744Z","comments":true,"top":null,"path":"api/articles/Install/hello-world.json","realPath":null,"excerpt":null,"keywords":null,"cover":"/images/background/hello.jpg","content":null,"raw":null,"categories":[{"name":"博客","path":"api/categories/博客.json"},{"name":"安装","path":"api/categories/安装.json"}],"tags":[{"name":"hexo","path":"api/tags/hexo.json"},{"name":"主题","path":"api/tags/主题.json"}]},{"title":"Gitalk 评论踩坑","slug":"Other/gitalk-error","date":"2022-05-24T09:57:13.000Z","updated":"2023-11-29T02:42:01.746Z","comments":true,"top":null,"path":"api/articles/Other/gitalk-error.json","realPath":null,"excerpt":null,"keywords":null,"cover":"/images/background/gitalk-error.jpg","content":null,"raw":null,"categories":[{"name":"博客","path":"api/categories/博客.json"},{"name":"踩坑","path":"api/categories/踩坑.json"}],"tags":[{"name":"gitalk","path":"api/tags/gitalk.json"},{"name":"踩坑","path":"api/tags/踩坑.json"},{"name":"报错","path":"api/tags/报错.json"}]}]}